README
setup.py
bin/fchart
bin/tyc2_to_binary
fchart/__init__.py
fchart/all.py
fchart/astrocalc.py
fchart/deepsky.py
fchart/deepsky_catalog.py
fchart/deepsky_object.py
fchart/eps.py
fchart/fonts.py
fchart/graphics_interface.py
fchart/label_potential.py
fchart/pdf.py
fchart/revngc.py
fchart/saguaro.py
fchart/skymap_engine.py
fchart/star_catalog.py
fchart.egg-info/PKG-INFO
fchart.egg-info/SOURCES.txt
fchart.egg-info/dependency_links.txt
fchart.egg-info/requires.txt
fchart.egg-info/top_level.txt