Metadata-Version: 1.0
Name: fchart
Version: 0.3
Summary: Collection of Python scripts to make beautiful deepsky finder charts in various formats
Home-page: https://github.com/Fingel/fchart
Author: Michiel Brentjens <brentjens@astron.nl>, Austin Riba <root@austinriba.com>
Author-email: root@austinriba.com
License: GPLv2
Keywords: fchart starchart star charts finder chart astronomy map
Platform: UNKNOWN
